packages/HostelAffairs.py
packages/__init__.py
HA_IITB-0.1.0.dist-info/LICENSE
HA_IITB-0.1.0.dist-info/METADATA
HA_IITB-0.1.0.dist-info/WHEEL
HA_IITB-0.1.0.dist-info/top_level.txt
HA_IITB-0.1.0.dist-info/RECORD
